{
"oyywiwginoongwvcaxdh223j":["adinayoffie","Adina M. Yoffie"],
"2x7zed7ivbvesihocr4jbdlx":["yofrilyo","Frilyo 💛"],
"q2g4nmnjqzgostvldtihk3hz":["galyoffe","Gal Yoffe"],
"mqw3us65v72u7x6o64yngyfj":["littlebumblevee","🍩 Yofi! 🔞 ➡️ Sacanime Winter 24"],
"5yd7udstsswudlt7zfuma3yc":["werewolfpussy","yofie2011cool"],
"ajoej6utd2aycfr7n3zk6a4x":["yofukit","Demi"],
"6yoycdo2iz3ne4qerg2gvedq":"yofukaya",
"nbiawgijlssgamgff2o5ulfa":["yofuibobo","MK-BOBO"],
"3oh3ynrl3ziaooithd3a2xgp":["yofal","Marc LaFoy"],
"kjy2smldnp3zlqxnpbynmihn":["yofckz","я пєрдолє"],
"chbufzklmt5uulvta6briquk":["yofou","Yofou"],
"rryzj2pyepuhffptysciwcl4":"yofukasi",
"sobivm47fer7ebwbao4uesbr":["yoffitofi","ההיא"],
"xv65yievfi6glpkmqh72ch4k":["yofver685","將yiK"],
"vsle2zxvsqp5bfpjy2i63kvd":["yoff","Suletta Mercury"],
"2ze35xsnzmx26qngf6rrxevu":["yofizz","FizzyStardust"],
"egje7knxyzvhn2gteiskazbw":"yofoxtrip",
"2jkasbc7pflfe2esc7ercpjb":["yofa","Yofa"],
"kvohhwtjnbs6zd42exuso743":["yofi","yofi"],
"aztcq6z6mrzzbvp5a2edv4py":"yofrancisco",
"p2qmygosodwmzqqb3snb6hne":"yofalon"
}
