{
"jnrkt4cjd33nfyn6lmf7fkgh":["chanyeool","Yezra 先輩"],
"qj47lmu6c2adgypd3ith46d3":["cyezidhunter","Carlo Yezidhunter"],
"lz3hsc4vybs3alhvxvtahxtg":["sanfyezerskiy","San F. Yezerskiy"],
"p4cejqyiktk7s7rtgbvyi5d7":["superstripez","Yezzir"],
"lkquveqip5zjhz6pehmg7l5l":["yezzurp","yezzurp"],
"diu6gvixxahdollcyen7bmgf":"yezdan",
"qtdh3qzairjroukoqtelwxm6":"yezzziam",
"jcijdxhid4ga5biy2nkv4v4o":["yezir","yezir °"],
"p3bbd2y6asc4sstxgtseqg47":["yezzir","Hughie"],
"hvtgarboldy6zws4hhfqmc2k":["yezh","Yezh 🇺🇦"],
"rs4lajwlb2sqgakfqeqbxcf5":["yezarou","Ruby"],
"odju62sjf6c7v35nc2akytrl":"yezzet",
"g7vrusg3bglb6fqcgl6r7ivq":"yezoart",
"fgjynpn5mesk5twpzueigqnu":["yezt","Yezt"],
"lzm32y2dszph2woj4tjht7nq":["yezhik","Ёжик Крымский"],
"zm7tkrod2doaxljjtgll3fr3":["yezzyie","Jessica Rakäthe"],
"2e57czeej5u3jrtznkplka5u":["yezma","Yezma"],
"pa263cdddnnlvboqrb5qji6h":["yezixxx","요코"],
"7ibprftycgmsjvqk7v76hxzm":"yezuur",
"a4rhb2yng3z7xzevhfzxfrdv":["yezz","yezz"],
"eriil2vmxu373nwcyoxljzwc":"yeziest"
}
